setup.cfg
setup.py
chickens/__init__.py
chickens/__main__.py
chickens/chicken.py
chickens.egg-info/PKG-INFO
chickens.egg-info/SOURCES.txt
chickens.egg-info/dependency_links.txt
chickens.egg-info/not-zip-safe
chickens.egg-info/requires.txt
chickens.egg-info/top_level.txt