Metadata-Version: 1.0
Name: chickens
Version: 1.8.6
Summary: chickens
Home-page: https://github.com/Necrolisk/chickens
Author: Mark Scoble
Author-email: scoble.mr@gmail.com
License: UNKNOWN
Keywords: chicken,CHICKEN,CHICKENS,chickens
Platform: UNKNOWN
